from dataclasses import dataclass

@dataclass()
class Bytecode:
    STOP_CODE = 0x00
    POP_TOP = 0x01
    ROT_TWO = 0x02
    ROT_THREE = 0x03
    DUP_TOP = 0x04
    ROT_FOUR = 0x05
    NOP = 0x09
    UNARY_POSITIVE = 0x0A
    UNARY_NEGATIVE = 0x0B
    UNARY_NOT = 0x0C
    UNARY_CONVERT = 0x0D
    UNARY_INVERT = 0x0F
    LIST_APPEND = 0x12
    BINARY_POWER = 0x13
    BINARY_MULTIPLY = 0x14
    BINARY_DIVIDE = 0x15
    BINARY_MODULO = 0x16
    BINARY_ADD = 0x17
    BINARY_SUBTRACT = 0x18
    BINARY_SUBSCR = 0x19
    BINARY_FLOOR_DIVIDE = 0x1A
    BINARY_TRUE_DIVIDE = 0x1B
    INPLACE_FLOOR_DIVIDE = 0x1C
    INPLACE_TRUE_DIVIDE = 0x1D
    SLICE = 0x1E
    SLICE_1 = 0x1F
    SLICE_2 = 0x20
    SLICE_3 = 0x21
    STORE_SLICE = 0x28
    STORE_SLICE_1 = 0x29
    STORE_SLICE_2 = 0x2A
    STORE_SLICE_3 = 0x2B
    DELETE_SLICE = 0x32
    DELETE_SLICE_1 = 0x33
    DELETE_SLICE_2 = 0x34
    DELETE_SLICE_3 = 0x35
    INPLACE_ADD = 0x37
    INPLACE_SUBTRACT = 0x38
    INPLACE_MULTIPLY = 0x39
    INPLACE_DIVIDE = 0x3A
    INPLACE_MODULO = 0x3B
    STORE_SUBSCR = 0x3C
    DELETE_SUBSCR = 0x3D
    BINARY_LSHIFT = 0x3E
    BINARY_RSHIFT = 0x3F
    BINARY_AND = 0x40
    BINARY_XOR = 0x41
    BINARY_OR = 0x42
    INPLACE_POWER = 0x43
    GET_ITER = 0x44
    PRINT_EXPR = 0x46
    PRINT_ITEM = 0x47
    PRINT_NEWLINE = 0x48
    PRINT_ITEM_TO = 0x49
    PRINT_NEWLINE_TO = 0x4A
    INPLACE_LSHIFT = 0x4B
    INPLACE_RSHIFT = 0x4C
    INPLACE_AND = 0x4D
    INPLACE_XOR = 0x4E
    INPLACE_OR = 0x4F
    BREAK_LOOP = 0x50
    WITH_CLEANUP = 0x51
    LOAD_LOCALS = 0x52
    RETURN_VALUE = 0x53
    IMPORT_STAR = 0x54
    EXEC_STMT = 0x55
    YIELD_VALUE = 0x56
    POP_BLOCK = 0x57
    END_FINALLY = 0x58
    BUILD_CLASS = 0x59
    STORE_NAME = 0x5A
    DELETE_NAME = 0x5B
    UNPACK_SEQUENCE = 0x5C
    FOR_ITER = 0x5D
    STORE_ATTR = 0x5F
    DELETE_ATTR = 0x60
    STORE_GLOBAL = 0x61
    DELETE_GLOBAL = 0x62
    DUP_TOPX = 0x63
    LOAD_CONST = 0x64
    LOAD_NAME = 0x65
    BUILD_TUPLE = 0x66
    BUILD_LIST = 0x67
    BUILD_MAP = 0x68
    LOAD_ATTR = 0x69
    COMPARE_OP = 0x6A
    IMPORT_NAME = 0x6B
    IMPORT_FROM = 0x6C
    JUMP_FORWARD = 0x6E
    JUMP_IF_FALSE = 0x6F
    JUMP_IF_TRUE = 0x70
    JUMP_ABSOLUTE = 0x71
    LOAD_GLOBAL = 0x74
    CONTINUE_LOOP = 0x77
    SETUP_LOOP = 0x78
    SETUP_EXCEPT = 0x79
    SETUP_FINALLY = 0x7A
    LOAD_FAST = 0x7C
    STORE_FAST = 0x7D
    DELETE_FAST = 0x7E
    RAISE_VARARGS = 0x82
    CALL_FUNCTION = 0x83
    MAKE_FUNCTION = 0x84
    BUILD_SLICE = 0x85
    MAKE_CLOSURE = 0x86
    LOAD_CLOSURE = 0x87
    LOAD_DEREF = 0x88
    STORE_DEREF = 0x89
    CALL_FUNCTION_VAR = 0x8C
    CALL_FUNCTION_KW = 0x8D
    CALL_FUNCTION_VAR_KW = 0x8E
    EXTENDED_ARG = 0x8F
